flowops/__init__.py
flowops/__main__.py
flowops/flow.py
flowops/warp.py
flowops/io/__init__.py
flowops/io/format.py
flowops/io/read_write.py
flowops/io/typings.py
flowops/io/utils.py
flowops-0.1.0.dist-info/LICENSE
flowops-0.1.0.dist-info/METADATA
flowops-0.1.0.dist-info/WHEEL
flowops-0.1.0.dist-info/entry_points.txt
flowops-0.1.0.dist-info/top_level.txt
flowops-0.1.0.dist-info/RECORD
